RSS_OPML_to_Markdown/RSS_OPML_to_Markdown.py
RSS_OPML_to_Markdown/__init__.py
RSS_OPML_to_Markdown-0.0.7.dist-info/LICENSE
RSS_OPML_to_Markdown-0.0.7.dist-info/METADATA
RSS_OPML_to_Markdown-0.0.7.dist-info/WHEEL
RSS_OPML_to_Markdown-0.0.7.dist-info/entry_points.txt
RSS_OPML_to_Markdown-0.0.7.dist-info/top_level.txt
RSS_OPML_to_Markdown-0.0.7.dist-info/RECORD
