Metadata-Version: 2.1
Name: RSS-OPML-to-Markdown
Version: 0.0.7
Summary: Convert RSS OPML file to Markdown - easy to read and share
Home-page: https://github.com/idealclover/RSS-OPML-to-Markdown
Author: idealclover
Author-email: shadowspacex@163.com
License: UNKNOWN
Platform: UNKNOWN
Classifier: Programming Language :: Python :: 3
Classifier: License :: OSI Approved :: MIT License
Classifier: Operating System :: OS Independent
Requires-Dist: listparser
Requires-Dist: tabulate
